Metadata-Version: 1.1
Name: webviewhooks
Version: 0.0.3
Summary: get webView html DOM tree
Home-page: UNKNOWN
Author: looper
Author-email: looperchu2018@gmail.com
License: MIT
Platform: UNKNOWN
Classifier: Programming Language :: Python :: 3
Classifier: License :: OSI Approved :: MIT License
Classifier: Operating System :: OS Independent
